backend_config.py
commands/__init__.py
commands/analyze_install_steps.py
commands/bootstrap.py
commands/clean.py
commands/config.py
commands/copy/__init__.py
commands/copy/backend.py
commands/copy/frontend.py
commands/copy/utils.py
commands/credstore_cli.py
commands/delete.py
commands/doctor.py
commands/fast_sync.py
commands/flags.py
commands/git.py
commands/jobs.py
commands/logs/__init__.py
commands/logs/clean.py
commands/logs/download.py
commands/oidc_cli.py
commands/refresh.py
commands/registry_cli.py
commands/setup.py
commands/show_urls.py
commands/tools.py
commands/verify.py
doctor/__init__.py
doctor/base.py
doctor/cleanup.py
doctor/config.py
doctor/oidc.py
doctor/stacks.py
frontend_build.py
frontend_deploy.py
installer/__init__.py
installer/execution.py
installer/steps.py
installer/ui.py
installer/utils.py
lambda_config.py
main.py
oidc/__init__.py
oidc/api_registration.py
oidc/cleanup.py
oidc/client_redirect.py
oidc/credential_storage.py
oidc/frontend_config.py
oidc/orchestrator.py
oidc/prerequisites.py
oidc/provider_registration.py
oidc/verification.py
utils/__init__.py
utils/api_gateway_utils.py
utils/api_utils.py
utils/app_config.py
utils/aws_utils.py
utils/base_cli.py
utils/client_factory.py
utils/cloudformation_utils.py
utils/command_utils.py
utils/component_registry.py
utils/config_utils.py
utils/console_utils.py
utils/direct_invoke_client.py
utils/dynamodb_utils.py
utils/jwt_utils.py
utils/logging_utils.py
utils/oidc_config_utils.py
utils/path_config.py
utils/precheck.py
utils/project_config.py
utils/shared_console.py
utils/stack_config.py
utils/system_utils.py
utils/umd_credential_store.py
verify_clients.py
docr_cli-0.1.66.dist-info/METADATA
docr_cli-0.1.66.dist-info/WHEEL
docr_cli-0.1.66.dist-info/entry_points.txt
docr_cli-0.1.66.dist-info/RECORD
