Metadata-Version: 2.3
Name: docr-cli
Version: 0.1.66
Summary: AI Solutions Document Review CLI tools for development workflows
Author: Christopher David Mann
Author-email: cmann@umd.edu
Requires-Python: >=3.11,<4.0
Classifier: Programming Language :: Python :: 3
Classifier: Programming Language :: Python :: 3.11
Classifier: Programming Language :: Python :: 3.12
Classifier: Programming Language :: Python :: 3.13
Requires-Dist: boto3 (>=1.35.60,<2.0.0)
Requires-Dist: loguru (>=0.7.2,<0.8.0)
Requires-Dist: packaging (>=24.0,<25.0)
Requires-Dist: pydantic (>=2.0.0,<3.0.0)
Requires-Dist: pyjwt (>=2.9.0,<3.0.0)
Requires-Dist: python-dotenv (>=1.0.1,<2.0.0)
Requires-Dist: pyyaml (>=6.0.1,<7.0.0)
Requires-Dist: requests (>=2.32.3,<3.0.0)
Requires-Dist: rich (>=14.0.0,<15.0.0)
Requires-Dist: tomli-w (>=1.0.0,<2.0.0)
Requires-Dist: typer (>=0.15.4,<0.16.0)
